{
  "book_id": "JOB",
  "chapter": 25,
  "verses": [
    {
      "verse": 1,
      "text": "Ὑπολαβὼν δὲ Βαλδὰδ ὁ Σαυχίτης, λέγει,"
    },
    {
      "verse": 2,
      "text": "Τί γὰρ προοίμιον ἢ φόβος παρʼ αὐτοῦ ὁ ποιῶν τὴν σύμπασαν ἐν ὑψιστῳ;"
    },
    {
      "verse": 3,
      "text": "Μὴ γάρ τις ὑπολάβοι ὅτι ἐστὶ παρέλκυσις πειραταῖς· ἐπὶ τίνας δὲ οὐκ ἐπελεύσεται ἔνεδρα παρʼ αὐτοῦ;"
    },
    {
      "verse": 4,
      "text": "Πῶς γὰρ ἔσται δίκαιος βροτὸς ἔναντι Κυρίου; ἢ τίς ἂν ἀποκαθαρίσαι αὐτὸν γεννητὸς γυναικός;"
    },
    {
      "verse": 5,
      "text": "Εἰ σελήνῃ συντάσσει, καὶ οὐκ ἐπιφαύσκει, ἄστρα δὲ οὐ καθαρὰ ἐναντίον αὐτοῦ."
    },
    {
      "verse": 6,
      "text": "Ἔα δὲ, ἄνθρωπος σαπρία, καὶ υἱὸς ἀνθρώπου σκώληξ."
    }
  ]
}