{
  "book_id": "PSA",
  "chapter": 12,
  "verses": [
    {
      "verse": 1,
      "text": "Εἰς τὸ τέλος, ψαλμὸς τῷ Δαυίδ. Ἕως πότε Κύριε ἐπιλήσῃ μου, εἰς τέλος; ἕως πότε ἀποστρέψεις τὸ πρόσωπόν σου ἀπʼ ἐμοῦ;"
    },
    {
      "verse": 2,
      "text": "Ἕως τίνος θήσομαι βουλὰς ἐν ψυχῇ μου, ὀδύνας ἐν καρδίᾳ μου ἡμέρας; ἕως πότε ὑψωθήσεται ὁ ἐχθρός μου ἐπʼ ἐμέ;"
    },
    {
      "verse": 3,
      "text": "Ἐπίβλεψον, εἰσάκουσόν μου, Κύριε ὁ Θεός μου· φώτισον τοὺς ὀφθαλμούς μου, μή ποτε ὑπνώσω εἰς θάνατον·"
    },
    {
      "verse": 4,
      "text": "μή ποτε εἴποι ὁ ἐχθρός μου, ἴσχυσα πρὸς αὐτόν· οἱ θλίβοντές με ἀγαλλιάσονται ἐὰν σαλευθῶ."
    },
    {
      "verse": 5,
      "text": "Ἐγὼ δὲ ἐπὶ τῷ ἐλέει σου ἤλπισα· ἀγαλλιάσεται ἡ καρδία μου ἐν τῷ σωτηρίῳ σου."
    },
    {
      "verse": 6,
      "text": "Ἄσω τῷ Κυρίῳ τῷ εὐεργετήσαντί με, καὶ ψαλῶ τῷ ὀνόματι Κυρίου τοῦ ὑψίστου."
    }
  ]
}