{
  "book_id": "PSA",
  "chapter": 4,
  "verses": [
    {
      "verse": 1,
      "text": "For the end, a Song of David among \\add the\\add* Psalms."
    },
    {
      "verse": 2,
      "text": "When I called upon \\add him\\add*, the God of my righteousness heard me: Thou hast made room for me in tribulation; Pity me, and hearken to my prayer."
    },
    {
      "verse": 3,
      "text": "O ye sons of men, how long \\add will ye be\\add* slow of heart? Wherefore do ye love vanity, and seek falsehood? Pause."
    },
    {
      "verse": 4,
      "text": "But know ye that the Lord has done wondrous things for his holy one: The Lord will hear me when I cry to him."
    },
    {
      "verse": 5,
      "text": "Be ye angry, and sin not; Feel compunction upon your beds For what ye say in your hearts. Pause."
    },
    {
      "verse": 6,
      "text": "Offer the sacrifice of righteousness, And trust in the Lord."
    },
    {
      "verse": 7,
      "text": "Many say, Who will show us good things? The light of thy countenance, O Lord, has been manifested toward us."
    },
    {
      "verse": 8,
      "text": "Thou hast put gladness into my heart: They have been satisfied with the fruit of their corn and wine and oil."
    },
    {
      "verse": 9,
      "text": "I will both lie down in peace and sleep: For thou, Lord, only hast caused me to dwell securely."
    }
  ]
}